ml_wac/__init__.py
ml_wac/wac.py
ml_wac/data/__init__.py
ml_wac/data/models/__init__.py
ml_wac/data/models/decision_tree.model
ml_wac/data/models/logistic_regression.model
ml_wac/data/models/support_vector_machine.model
ml_wac/data/models/xgboost.model
ml_wac/data/vectorizers/__init__.py
ml_wac/data/vectorizers/vectorizer.sklearn
ml_wac/tests/__init__.py
ml_wac/tests/model_inference_test.py
ml_wac/types/__init__.py
ml_wac/types/attack_type.py
ml_wac/types/model_type.py
ml_wac-1.1.dist-info/LICENSE
ml_wac-1.1.dist-info/METADATA
ml_wac-1.1.dist-info/WHEEL
ml_wac-1.1.dist-info/top_level.txt
ml_wac-1.1.dist-info/RECORD
